samplestamps/__init__.py
samplestamps/samplestamps.py
samplestamps/utils.py
samplestamps-0.6.0.dist-info/LICENSE
samplestamps-0.6.0.dist-info/WHEEL
samplestamps-0.6.0.dist-info/METADATA
samplestamps-0.6.0.dist-info/RECORD
