Metadata-Version: 2.1
Name: samplestamps
Version: 0.6.0
Summary: For converting between timestamps.
Home-page: https://github.com/janclemenslab/samplestamps
Author: Jan Clemens
Author-email: clemensjan@googlemail.com
Requires-Python: >=3.6
Classifier: License :: OSI Approved :: MIT License
Requires-Dist: numpy
Requires-Dist: scipy
